Metadata-Version: 1.0
Name: oms-probability
Version: 1.0
Summary: Gaussian and Binomial distributions
Home-page: UNKNOWN
Author: Hung Om
Author-email: hung.workspace@gmail.com
License: UNKNOWN
Platform: UNKNOWN
